{
  "datas": [
    {
      "signin": "admin",
      "password": "admin",
      "id": 1
    },
    {
      "signin": "ezaeaze",
      "password": "",
      "id": 2
    },
    {
      "signin": "a",
      "password": "",
      "id": 3
    },
    {
      "signin": "aa",
      "password": "",
      "id": 4
    },
    {
      "signin": "aa",
      "password": "a",
      "id": 5
    },
    {
      "signin": "aa",
      "password": "aa",
      "id": 6
    },
    {
      "signin": "aaazadaz",
      "password": "test\n",
      "id": 7
    },
    {
      "signin": "aaazadaz",
      "password": "testt\n",
      "id": 8
    },
    {
      "signin": "aaazadaz",
      "password": "testte\n",
      "id": 9
    },
    {
      "signin": "aaazadaz",
      "password": "testtes\n",
      "id": 10
    },
    {
      "signin": "aaazadaz",
      "password": "testtesa\n",
      "id": 11
    },
    {
      "signin": "aaazadaz",
      "password": "testtesaz\n",
      "id": 12
    },
    {
      "signin": "aaazadazazddz",
      "password": "testtesaz\n\n",
      "id": 13
    },
    {
      "signin": "aaazadazazddz",
      "password": "testtesaz\nd\n",
      "id": 14
    },
    {
      "signin": "aaazadazazddz",
      "password": "testtesaz\nda\n",
      "id": 15
    },
    {
      "signin": "aaazadazazddz",
      "password": "testtesaz\ndaz\n",
      "id": 16
    },
    {
      "signin": "ezaeaez",
      "password": "",
      "id": 17
    },
    {
      "signin": "dz",
      "password": "",
      "id": 18
    },
    {
      "signin": "dzad",
      "password": "da",
      "id": 19
    },
    {
      "signin": "dza",
      "password": "",
      "id": 20
    },
    {
      "signin": "d",
      "password": "",
      "id": 21
    },
    {
      "signin": "dzad",
      "password": "",
      "id": 22
    },
    {
      "signin": "dzad",
      "password": "daz",
      "id": 23
    },
    {
      "signin": "verif",
      "password": "v",
      "id": 24
    },
    {
      "signin": "eazeaze",
      "password": "",
      "id": 25
    },
    {
      "signin": "v",
      "password": "",
      "id": 26
    },
    {
      "signin": "ve",
      "password": "",
      "id": 27
    },
    {
      "signin": "verif",
      "password": "ve",
      "id": 28
    },
    {
      "signin": "verif",
      "password": "",
      "id": 29
    },
    {
      "signin": "verif",
      "password": "ver",
      "id": 30
    },
    {
      "signin": "veri",
      "password": "",
      "id": 31
    },
    {
      "signin": "verif",
      "password": "veri",
      "id": 32
    },
    {
      "signin": "verif",
      "password": "verif2",
      "id": 33
    },
    {
      "signin": "verif",
      "password": "verif",
      "id": 34
    },
    {
      "signin": "ver",
      "password": "",
      "id": 35
    },
    {
      "signin": "ezaezaeaez",
      "password": "",
      "id": 36
    },
    {
      "signin": "mainten",
      "password": "",
      "id": 37
    },
    {
      "signin": "maintena",
      "password": "",
      "id": 38
    },
    {
      "signin": "maintenan",
      "password": "",
      "id": 39
    },
    {
      "signin": "m",
      "password": "",
      "id": 40
    },
    {
      "signin": "maintenant",
      "password": "",
      "id": 41
    },
    {
      "signin": "ma",
      "password": "",
      "id": 42
    },
    {
      "signin": "mainte",
      "password": "",
      "id": 43
    },
    {
      "signin": "mai",
      "password": "",
      "id": 44
    },
    {
      "signin": "main",
      "password": "",
      "id": 45
    },
    {
      "signin": "maint",
      "password": "",
      "id": 46
    },
    {
      "signin": "maintenant",
      "password": "m",
      "id": 47
    },
    {
      "signin": "maintenant",
      "password": "mmaintena",
      "id": 48
    },
    {
      "signin": "maintenant",
      "password": "mma",
      "id": 49
    },
    {
      "signin": "maintenant",
      "password": "mmainten",
      "id": 50
    },
    {
      "signin": "maintenant",
      "password": "mmaintenan",
      "id": 51
    },
    {
      "signin": "maintenant",
      "password": "mmai",
      "id": 52
    },
    {
      "signin": "maintenant",
      "password": "mm",
      "id": 53
    },
    {
      "signin": "maintenant",
      "password": "m",
      "id": 54
    },
    {
      "signin": "main",
      "password": "",
      "id": 55
    },
    {
      "signin": "maint",
      "password": "",
      "id": 56
    },
    {
      "signin": "azeezae",
      "password": "",
      "id": 57
    },
    {
      "signin": "tes",
      "password": "",
      "id": 58
    },
    {
      "signin": "zadzad",
      "password": "",
      "id": 59
    },
    {
      "signin": "tesr",
      "password": "",
      "id": 60
    },
    {
      "signin": "t",
      "password": "",
      "id": 61
    },
    {
      "signin": "t",
      "password": "",
      "id": 62
    },
    {
      "signin": "dzadaz",
      "password": "",
      "id": 63
    },
    {
      "signin": "qqqq",
      "password": "",
      "id": 64
    },
    {
      "signin": "dzadzadd",
      "password": "",
      "id": 65
    },
    {
      "signin": "qqqq",
      "password": "",
      "id": 66
    },
    {
      "signin": "qqqq",
      "password": "q",
      "id": 67
    },
    {
      "signin": "q",
      "password": "",
      "id": 68
    },
    {
      "signin": "q",
      "password": "",
      "id": 69
    },
    {
      "signin": "qqq",
      "password": "",
      "id": 70
    },
    {
      "signin": "qqqq",
      "password": "q",
      "id": 71
    },
    {
      "signin": "qqqq",
      "password": "qq",
      "id": 72
    },
    {
      "signin": "qq",
      "password": "",
      "id": 73
    },
    {
      "signin": "qqqq",
      "password": "qq",
      "id": 74
    },
    {
      "sign": "dazdzad",
      "pass": "",
      "id": 75
    },
    {
      "sign": "dzadazdaz",
      "pass": "",
      "id": 76
    },
    {
      "id": 77
    },
    {
      "id": 78
    },
    {
      "pass": "",
      "id": 79
    },
    {
      "pass": "",
      "id": 80
    },
    {
      "id": 81
    },
    {
      "id": 82
    },
    {
      "pass": "",
      "id": 83
    },
    {
      "pass": "",
      "id": 84
    },
    {
      "id": 85
    },
    {
      "signin": "dzadzadazd",
      "password": "",
      "id": 86
    },
    {
      "signin": "dazdzad",
      "password": "",
      "id": 87
    },
    {
      "password": "",
      "id": 88
    },
    {
      "password": "",
      "id": 89
    },
    {
      "password": "",
      "id": 90
    },
    {
      "id": 91
    },
    {
      "id": 92
    },
    {
      "id": 93
    },
    {
      "id": 94
    },
    {
      "id": 95
    },
    {
      "id": 96
    },
    {
      "password": "",
      "id": 97
    },
    {
      "signin": "dazdzdadz",
      "password": "",
      "id": 98
    },
    {
      "id": 99
    },
    {
      "signin": "dzadazzda",
      "password": "",
      "id": 100
    },
    {
      "id": 101
    },
    {
      "password": "",
      "id": 102
    },
    {
      "id": 103
    },
    {
      "password": "",
      "id": 104
    },
    {
      "id": 105
    },
    {
      "id": 106
    },
    {
      "signin": "dazdzdza",
      "password": "",
      "id": 107
    },
    {
      "signin": "dza",
      "password": "",
      "id": 108
    },
    {
      "signin": "d",
      "password": "",
      "id": 109
    },
    {
      "signin": "dazdzadaz",
      "password": "",
      "id": 110
    },
    {
      "signin": "dza",
      "password": "",
      "id": 111
    },
    {
      "signin": "dz",
      "password": "",
      "id": 112
    },
    {
      "signin": "dadaz",
      "password": "dazddzaaz\n",
      "id": 113
    },
    {
      "signin": "dzadza",
      "password": "",
      "id": 114
    },
    {
      "signin": "adzdaazd",
      "password": "",
      "id": 115
    },
    {
      "signin": "zazaa",
      "password": "",
      "id": 116
    },
    {
      "signin": "zaaazaa",
      "password": "",
      "id": 117
    },
    {
      "signin": "a",
      "password": "",
      "id": 118
    },
    {
      "signin": "a",
      "password": "",
      "id": 119
    },
    {
      "signin": "az",
      "password": "",
      "id": 120
    },
    {
      "signin": "az",
      "password": "",
      "id": 121
    },
    {
      "signin": "aza",
      "password": "",
      "id": 122
    },
    {
      "signin": "aza",
      "password": "",
      "id": 123
    },
    {
      "signin": "azad",
      "password": "",
      "id": 124
    },
    {
      "signin": "azad",
      "password": "",
      "id": 125
    },
    {
      "signin": "azadz",
      "password": "",
      "id": 126
    },
    {
      "signin": "azadz",
      "password": "",
      "id": 127
    },
    {
      "signin": "azadza",
      "password": "",
      "id": 128
    },
    {
      "signin": "azadza",
      "password": "",
      "id": 129
    },
    {
      "signin": "azadzad",
      "password": "",
      "id": 130
    },
    {
      "signin": "azadzad",
      "password": "",
      "id": 131
    },
    {
      "signin": "azadzada",
      "password": "",
      "id": 132
    },
    {
      "signin": "azadzada",
      "password": "",
      "id": 133
    },
    {
      "signin": "a",
      "password": "",
      "id": 134
    },
    {
      "signin": "a",
      "password": "",
      "id": 135
    },
    {
      "signin": "az",
      "password": "",
      "id": 136
    },
    {
      "signin": "az",
      "password": "",
      "id": 137
    },
    {
      "signin": "azd",
      "password": "",
      "id": 138
    },
    {
      "signin": "azdz",
      "password": "",
      "id": 139
    },
    {
      "signin": "TEST1",
      "password": "TEST2",
      "id": 140
    },
    {
      "signin": "TEST55",
      "password": "TESR",
      "id": 141
    },
    {
      "signin": "FINAL",
      "password": "FINALPASS\n\n\n",
      "id": 142
    },
    {
      "signin": "FFFFFFFFFFF",
      "password": "DDDDDDDDDDDDDDDD",
      "id": 143
    },
    {
      "signin": "aaaaaaaaaaaaaaa",
      "password": "hhhhhhhhhhhhhh\n",
      "id": 144
    },
    {
      "signin": "ffezfeaf",
      "password": "fafaef",
      "id": 145
    },
    {
      "signin": "dazdzad",
      "password": "dzaddddddd\n",
      "id": 146
    },
    {
      "signin": "dazdzda",
      "password": "ddddd",
      "id": 147
    },
    {
      "signin": "dzadazd",
      "password": "dzadzd\n",
      "id": 148
    },
    {
      "signin": "aaaaaaaaaaaaa",
      "password": "ssssssssssssssssssssss",
      "id": 149
    },
    {
      "signin": "ssssssssssssssssssss",
      "password": "qqqqqqqqqqqqqqqqqqqqqqqqqqq",
      "id": 150
    },
    {
      "signin": "ggggggggggggg",
      "password": "hhhhhhhhhhh",
      "id": 151
    },
    {
      "signin": "jjjjjjjjjjjjj",
      "password": "kkkkkkkkkkkkkkkkkk",
      "id": 152
    },
    {
      "signin": "ggggggggg",
      "password": "qqqqqqqqqqqqq\n",
      "id": 153
    },
    {
      "signin": "qqqqqqqqqqqqq",
      "password": "wwwwwwwwwwwwwww",
      "id": 154
    },
    {
      "signin": "aaa",
      "password": "qqqqqqqq\n",
      "id": 155
    },
    {
      "signin": "qqqqqqqq",
      "password": "sssssssssssssss",
      "id": 156
    },
    {
      "signin": "aaa",
      "password": "qqqqqqqqqqq",
      "id": 157
    },
    {
      "signin": "a",
      "password": "aqqqqqqqqqqq",
      "id": 158
    },
    {
      "signin": "aaaa",
      "password": "zzzzzzz",
      "id": 159
    },
    {
      "signin": "aaa",
      "password": "qqqqqq",
      "id": 160
    },
    {
      "signin": "aaaq",
      "password": "qqqqqqqqqq",
      "id": 161
    },
    {
      "signin": "aaz",
      "password": "zzz",
      "id": 162
    },
    {
      "signin": "aazz",
      "password": "zaza",
      "id": 163
    },
    {
      "signin": "aaaaq",
      "password": "qqqqqqqqqqq",
      "id": 164
    },
    {
      "signin": "qq",
      "password": "sssssss",
      "id": 165
    },
    {
      "signin": "aa",
      "password": "zzz",
      "id": 166
    },
    {
      "signin": "qqqqqq",
      "password": "sssssssss",
      "id": 167
    },
    {
      "signin": "qqqqqqqqqq",
      "password": "vvvvvvvvvvvvv",
      "id": 168
    },
    {
      "signin": "aaa",
      "password": "bbbbbbbb",
      "id": 169
    },
    {
      "signin": "fffffffff",
      "password": "cccccccccccccccccc",
      "id": 170
    },
    {
      "signin": "qqq",
      "password": "xxxxxxxxxxxx",
      "id": 171
    },
    {
      "signin": "aaaa",
      "password": "wwwwwwwwwww",
      "id": 172
    },
    {
      "signin": "aaaa",
      "password": "qqqqqqqqqq",
      "id": 173
    },
    {
      "signin": "aaaa",
      "password": "qqqqqqqqq",
      "id": 174
    },
    {
      "signin": "hhhhhhhh",
      "password": "jjjjjjjjj",
      "id": 175
    },
    {
      "signin": "aaaaaa",
      "password": "xxxxxxxxx",
      "id": 176
    },
    {
      "signin": "aaa",
      "password": "zzzz",
      "id": 177
    },
    {
      "signin": "qqqq",
      "password": "wwwww",
      "id": 178
    },
    {
      "signin": "aaaa",
      "password": "fffffffff",
      "id": 179
    },
    {
      "signin": "fhhhhhhhh",
      "password": "bbbbbbbbbbb",
      "id": 180
    },
    {
      "signin": "aaa",
      "password": "ssssssss",
      "id": 181
    },
    {
      "signin": "qqqqqqqqqqqq",
      "password": "bbbbbbbbbbb",
      "id": 182
    },
    {
      "signin": "dddddd",
      "password": "xxxxxxxxxxxxxx",
      "id": 183
    },
    {
      "signin": "qqqqqqqqqq",
      "password": "wwwwwwwwwww",
      "id": 184
    },
    {
      "signin": "vvvvvvvvv",
      "password": "bbbbbbbbbbbbbb",
      "id": 185
    },
    {
      "signin": "zzz",
      "password": "cccccccccccc",
      "id": 186
    },
    {
      "signin": "vvvvvvv",
      "password": "bbbbbbbbbbbbbb",
      "id": 187
    },
    {
      "signin": "vvvvxxxxxxxxxxx",
      "password": "",
      "id": 188
    },
    {
      "signin": "kkkkkkk",
      "password": "llllllllll",
      "id": 189
    },
    {
      "signin": "hhhhhhhhhhh",
      "password": "kkkkkkkkkkk",
      "id": 190
    },
    {
      "signin": "hello\nhello",
      "password": "hello",
      "id": 191
    },
    {
      "signin": "qqqqqqqqqq",
      "password": "cccccccccccccc",
      "id": 192
    },
    {
      "signin": "az",
      "password": "zss",
      "id": 193
    },
    {
      "signin": "qqqq",
      "password": "wwwwwwwwww",
      "id": 194
    },
    {
      "signin": "vvvv",
      "password": "ffffff",
      "id": 195
    },
    {
      "signin": "s",
      "password": "xxx",
      "id": 196
    },
    {
      "signin": "hhhhhh",
      "password": "jjjjjj",
      "id": 197
    },
    {
      "signin": "zzz",
      "password": "vvv",
      "id": 198
    },
    {
      "signin": "az",
      "password": "xxx",
      "id": 199
    },
    {
      "signin": "az",
      "password": "ddd",
      "id": 200
    },
    {
      "signin": "dd",
      "password": "vvv",
      "id": 201
    },
    {
      "signin": "azd",
      "password": "zzzz",
      "id": 202
    },
    {
      "signin": "hello\nhello",
      "password": "hello",
      "id": 203
    },
    {
      "signin": "dzdnaozdnz",
      "password": "qqqqqqqqqqqq",
      "id": 204
    },
    {
      "signin": "hello\nhello",
      "password": "hello",
      "id": 205
    },
    {
      "signin": "mawa",
      "password": "mawa",
      "id": 206
    },
    {
      "signin": "last",
      "password": "last",
      "id": 207
    },
    {
      "signin": "gggggggg",
      "password": "nnnnnnnnnnn",
      "id": 208
    },
    {
      "signin": "qqqqqqqqq",
      "password": "wwwwwwwwwwww",
      "id": 209
    },
    {
      "signin": "kkk",
      "password": "lll",
      "id": 210
    },
    {
      "signin": "hello",
      "password": "hello\n",
      "id": 211
    },
    {
      "signin": "admin",
      "password": "admin",
      "id": 212
    },
    {
      "signin": "hello",
      "password": "hello",
      "id": 213
    },
    {
      "signin": "hello",
      "password": "hello",
      "id": 214
    },
    {
      "signin": "admin",
      "password": "admin",
      "id": 215
    },
    {
      "signin": "bbbbbb",
      "password": "kkkkkkkkkk",
      "id": 216
    },
    {
      "signin": "hello",
      "password": "hello\n",
      "id": 217
    },
    {
      "signin": "admin",
      "password": "admin",
      "id": 218
    },
    {
      "signin": "hello",
      "password": "hello\n",
      "id": 219
    },
    {
      "signin": "admin",
      "password": "admin",
      "id": 220
    },
    {
      "signin": "admin",
      "password": "admin\n",
      "id": 221
    },
    {
      "signin": "dddd",
      "password": "xxxxxxx",
      "id": 222
    },
    {
      "signin": "fffff",
      "password": "vvvvvv",
      "id": 223
    },
    {
      "signin": "hello",
      "password": "hello",
      "id": 224
    },
    {
      "signin": "zzz",
      "password": "qqqqqqqq",
      "id": 225
    },
    {
      "signin": "hello",
      "password": "hello",
      "id": 226
    },
    {
      "signin": "admin",
      "password": "admin",
      "id": 227
    },
    {
      "signin": "hello",
      "password": "hello",
      "id": 228
    },
    {
      "signin": "hello",
      "password": "hello",
      "id": 229
    },
    {
      "signin": "lllll",
      "password": "mmmmmmmm",
      "id": 230
    },
    {
      "signin": "nsozidnoaz",
      "password": "mmmmmmmmm",
      "id": 231
    },
    {
      "signin": "qq",
      "password": "www",
      "id": 232
    },
    {
      "signin": "never",
      "password": "aaaa",
      "id": 233
    },
    {
      "signin": "never",
      "password": "ne\n",
      "id": 234
    },
    {
      "signin": "never",
      "password": "never\n",
      "id": 235
    },
    {
      "signin": "never",
      "password": "aaa",
      "id": 236
    },
    {
      "signin": "never",
      "password": "aa",
      "id": 237
    },
    {
      "signin": "never",
      "password": "lll",
      "id": 238
    },
    {
      "signin": "never",
      "password": "adzda",
      "id": 239
    },
    {
      "signin": "never",
      "password": "sqqqq",
      "id": 240
    },
    {
      "signin": "aazd",
      "password": "ddz",
      "id": 241
    },
    {
      "signin": "admin",
      "password": "admin\n",
      "id": 242
    },
    {
      "signin": "admin",
      "password": "admin",
      "id": 243
    },
    {
      "signin": "admin",
      "password": "admin",
      "id": 244
    },
    {
      "signin": "admini",
      "password": "admin",
      "id": 245
    },
    {
      "signin": "admini",
      "password": "admin",
      "id": 246
    },
    {
      "signin": "admini",
      "password": "admini",
      "id": 247
    },
    {
      "signin": "never",
      "password": "never",
      "id": 248
    },
    {
      "signin": "never",
      "password": "never",
      "id": 249
    },
    {
      "signin": "never",
      "password": "never",
      "id": 250
    },
    {
      "signin": "never",
      "password": "naaaa",
      "id": 251
    },
    {
      "signin": "never",
      "password": "never",
      "id": 252
    },
    {
      "signin": "never",
      "password": "dzadazd",
      "id": 253
    },
    {
      "signin": "never",
      "password": "d,azpo,dazd",
      "id": 254
    },
    {
      "signin": "never",
      "password": "azdadd",
      "id": 255
    },
    {
      "signin": "never",
      "password": "nnn",
      "id": 256
    },
    {
      "signin": "never",
      "password": "laaa",
      "id": 257
    },
    {
      "signin": "never",
      "password": ",dpkazd,za",
      "id": 258
    },
    {
      "signin": "never",
      "password": "dazdzazda",
      "id": 259
    },
    {
      "signin": "never",
      "password": "dazdzd",
      "id": 260
    },
    {
      "signin": "never",
      "password": "aaaa",
      "id": 261
    },
    {
      "signin": "never",
      "password": "aaa",
      "id": 262
    },
    {
      "signin": "never",
      "password": "never",
      "id": 263
    },
    {
      "signin": "never",
      "password": "never",
      "id": 264
    },
    {
      "signin": "never",
      "password": "never",
      "id": 265
    },
    {
      "signin": "never",
      "password": "never",
      "id": 266
    },
    {
      "signin": "never",
      "password": "never",
      "id": 267
    },
    {
      "signin": "never",
      "password": "never",
      "id": 268
    },
    {
      "signin": "never",
      "password": "never",
      "id": 269
    },
    {
      "signin": "never",
      "password": "never",
      "id": 270
    },
    {
      "signin": "never",
      "password": "never",
      "id": 271
    },
    {
      "signin": "never",
      "password": "aaaa",
      "id": 272
    },
    {
      "signin": "never",
      "password": "aaaa",
      "id": 273
    },
    {
      "signin": "never",
      "password": "aaaa",
      "id": 274
    },
    {
      "signin": "never",
      "password": "aaaa",
      "id": 275
    },
    {
      "signin": "never",
      "password": "aaaa",
      "id": 276
    },
    {
      "signin": "never",
      "password": "aaaa",
      "id": 277
    },
    {
      "signin": "never",
      "password": "aaaa",
      "id": 278
    },
    {
      "signin": "never",
      "password": "aaaa",
      "id": 279
    },
    {
      "signin": "never",
      "password": "aaaa",
      "id": 280
    },
    {
      "signin": "never",
      "password": "aaaa",
      "id": 281
    },
    {
      "signin": "never",
      "password": "d;zad",
      "id": 282
    },
    {
      "signin": "never",
      "password": "d;zad",
      "id": 283
    },
    {
      "signin": "never",
      "password": "d;zad",
      "id": 284
    },
    {
      "signin": "never",
      "password": "d;zad",
      "id": 285
    },
    {
      "signin": "never",
      "password": "d;zad",
      "id": 286
    },
    {
      "signin": "never",
      "password": "d;zad",
      "id": 287
    },
    {
      "signin": "never",
      "password": "d;zad",
      "id": 288
    },
    {
      "signin": "never",
      "password": "d;zad",
      "id": 289
    },
    {
      "signin": "never",
      "password": "d;zad",
      "id": 290
    },
    {
      "signin": "never",
      "password": "d;zad",
      "id": 291
    },
    {
      "signin": "never",
      "password": "d;zad",
      "id": 292
    },
    {
      "signin": "never",
      "password": "d;zad",
      "id": 293
    },
    {
      "signin": "never",
      "password": "d;zad",
      "id": 294
    },
    {
      "signin": "never",
      "password": "d;zad",
      "id": 295
    },
    {
      "signin": "never",
      "password": "d;zad",
      "id": 296
    },
    {
      "signin": "never",
      "password": "d;zad",
      "id": 297
    },
    {
      "signin": "never",
      "password": "d;zad",
      "id": 298
    },
    {
      "signin": "never",
      "password": "d;zad",
      "id": 299
    },
    {
      "signin": "never",
      "password": "d;zad",
      "id": 300
    },
    {
      "signin": "never",
      "password": "d;zad",
      "id": 301
    },
    {
      "signin": "never",
      "password": "d;zad",
      "id": 302
    },
    {
      "signin": "never",
      "password": "d;zad",
      "id": 303
    },
    {
      "signin": "never",
      "password": "d;zad",
      "id": 304
    },
    {
      "signin": "never",
      "password": "d;zad",
      "id": 305
    },
    {
      "signin": "never",
      "password": "d,azpd,az",
      "id": 306
    },
    {
      "signin": "never",
      "password": "d,azpd,az",
      "id": 307
    },
    {
      "signin": "never",
      "password": "d,azpd,az",
      "id": 308
    },
    {
      "signin": "never",
      "password": "d,azpd,az",
      "id": 309
    },
    {
      "signin": "never",
      "password": "d,azpd,az",
      "id": 310
    },
    {
      "signin": "never",
      "password": "d,azpd,az",
      "id": 311
    },
    {
      "signin": "never",
      "password": "d,azpd,az",
      "id": 312
    },
    {
      "signin": "never",
      "password": "d,azpd,az",
      "id": 313
    },
    {
      "signin": "never",
      "password": "dnzadnaz",
      "id": 314
    },
    {
      "signin": "never",
      "password": "dnzadnaz",
      "id": 315
    },
    {
      "signin": "never",
      "password": "dnzadnaz",
      "id": 316
    },
    {
      "signin": "never",
      "password": "dnzadnaz",
      "id": 317
    },
    {
      "signin": "never",
      "password": "dnzadnaz",
      "id": 318
    },
    {
      "signin": "never",
      "password": "dnzadnaz",
      "id": 319
    },
    {
      "signin": "never",
      "password": "dnzadnaz",
      "id": 320
    },
    {
      "signin": "never",
      "password": "dnzadnaz",
      "id": 321
    },
    {
      "signin": "never",
      "password": "dnzadnaz",
      "id": 322
    },
    {
      "signin": "never",
      "password": "dnzadnaz",
      "id": 323
    },
    {
      "signin": "never",
      "password": "dnzadnaz",
      "id": 324
    },
    {
      "signin": "never",
      "password": "dnzadnaz",
      "id": 325
    },
    {
      "signin": "never",
      "password": "dnzadnaz",
      "id": 326
    },
    {
      "signin": "never",
      "password": "dnzadnaz",
      "id": 327
    },
    {
      "signin": "never",
      "password": "dnzadnaz",
      "id": 328
    },
    {
      "signin": "never",
      "password": "dnzadnaz",
      "id": 329
    },
    {
      "signin": "never",
      "password": "dnzadnaz",
      "id": 330
    },
    {
      "signin": "never",
      "password": "dnzadnaz",
      "id": 331
    },
    {
      "signin": "never",
      "password": "dnzadnaz",
      "id": 332
    },
    {
      "signin": "never",
      "password": "dnzadnaz",
      "id": 333
    },
    {
      "signin": "never",
      "password": "dnzadnaz",
      "id": 334
    },
    {
      "signin": "never",
      "password": "dnzadnaz",
      "id": 335
    },
    {
      "signin": "never",
      "password": "dnzadnaz",
      "id": 336
    },
    {
      "signin": "never",
      "password": "dnzadnaz",
      "id": 337
    },
    {
      "signin": "never",
      "password": "dnzadnaz",
      "id": 338
    },
    {
      "signin": "never",
      "password": "dnzadnaz",
      "id": 339
    },
    {
      "signin": "never",
      "password": "dnzadnaz",
      "id": 340
    },
    {
      "signin": "never",
      "password": "dnzadnaz",
      "id": 341
    },
    {
      "signin": "never",
      "password": "dnzadnaz",
      "id": 342
    },
    {
      "signin": "never",
      "password": "dnzadnaz",
      "id": 343
    },
    {
      "signin": "never",
      "password": "dnzadnaz",
      "id": 344
    },
    {
      "signin": "never",
      "password": "dnzadnaz",
      "id": 345
    },
    {
      "signin": "never",
      "password": "dnzadnaz",
      "id": 346
    },
    {
      "signin": "never",
      "password": "dnzadnaz",
      "id": 347
    },
    {
      "signin": "never",
      "password": "dnzadnaz",
      "id": 348
    },
    {
      "signin": "never",
      "password": "dnzadnaz",
      "id": 349
    },
    {
      "signin": "never",
      "password": "dnzadnaz",
      "id": 350
    },
    {
      "signin": "never",
      "password": "dnzadnaz",
      "id": 351
    },
    {
      "signin": "never",
      "password": "dnzadnaz",
      "id": 352
    },
    {
      "signin": "never",
      "password": "dnzadnaz",
      "id": 353
    },
    {
      "signin": "never",
      "password": "dnzadnaz",
      "id": 354
    },
    {
      "signin": "never",
      "password": "d,azdaz",
      "id": 355
    },
    {
      "signin": "never",
      "password": "d,azdaz",
      "id": 356
    },
    {
      "signin": "never",
      "password": "d,azdaz",
      "id": 357
    },
    {
      "signin": "never",
      "password": "d,azdaz",
      "id": 358
    },
    {
      "signin": "never",
      "password": "d,azdaz",
      "id": 359
    },
    {
      "signin": "never",
      "password": "d,azdaz",
      "id": 360
    },
    {
      "signin": "never",
      "password": "d,azdaz",
      "id": 361
    },
    {
      "signin": "never",
      "password": "d,azdaz",
      "id": 362
    },
    {
      "signin": "never",
      "password": "d,azdaz",
      "id": 363
    },
    {
      "signin": "never",
      "password": "d,azdaz",
      "id": 364
    },
    {
      "signin": "never",
      "password": "d,azdaz",
      "id": 365
    },
    {
      "signin": "never",
      "password": "d,azdaz",
      "id": 366
    },
    {
      "signin": "never",
      "password": "aaaa\n",
      "id": 367
    },
    {
      "signin": "never",
      "password": "aaaa\n",
      "id": 368
    },
    {
      "signin": "never",
      "password": "aaaa\n",
      "id": 369
    },
    {
      "signin": "never",
      "password": "aaaa\n",
      "id": 370
    },
    {
      "signin": "never",
      "password": "aaaa\n",
      "id": 371
    },
    {
      "signin": "never",
      "password": "aaaa\n",
      "id": 372
    },
    {
      "signin": "never",
      "password": "aaaa\n",
      "id": 373
    },
    {
      "signin": "never",
      "password": "aaaa\n",
      "id": 374
    },
    {
      "signin": "never",
      "password": "aaaa\n",
      "id": 375
    },
    {
      "signin": "never",
      "password": "aaaa\n",
      "id": 376
    },
    {
      "signin": "never",
      "password": "aaaa\n",
      "id": 377
    },
    {
      "signin": "never",
      "password": "aaaa\n",
      "id": 378
    },
    {
      "signin": "never",
      "password": "aaaa\n",
      "id": 379
    },
    {
      "signin": "never",
      "password": "aaaa\n",
      "id": 380
    },
    {
      "signin": "never",
      "password": "aaaaaaa",
      "id": 381
    },
    {
      "signin": "never",
      "password": "aaaaaaa",
      "id": 382
    },
    {
      "signin": "never",
      "password": "aaaaaaa",
      "id": 383
    },
    {
      "signin": "never",
      "password": "aaaaaaa",
      "id": 384
    },
    {
      "signin": "never",
      "password": "aaaaaaa",
      "id": 385
    },
    {
      "signin": "never",
      "password": "aaaaaaa",
      "id": 386
    },
    {
      "signin": "never",
      "password": "aaaaaaa",
      "id": 387
    },
    {
      "signin": "never",
      "password": "aaaaaaa",
      "id": 388
    },
    {
      "signin": "never",
      "password": "aaaaaaa",
      "id": 389
    },
    {
      "signin": "never",
      "password": "aaaaaaa",
      "id": 390
    },
    {
      "signin": "never",
      "password": "aaaaaaa",
      "id": 391
    },
    {
      "signin": "never",
      "password": "aaaaaaa",
      "id": 392
    },
    {
      "signin": "never",
      "password": "dazp^dkaz",
      "id": 393
    },
    {
      "signin": "never",
      "password": "dazp^dkaz",
      "id": 394
    },
    {
      "signin": "never",
      "password": "dazp^dkaz",
      "id": 395
    },
    {
      "signin": "never",
      "password": "dazp^dkaz",
      "id": 396
    },
    {
      "signin": "never",
      "password": "dazp^dkaz",
      "id": 397
    },
    {
      "signin": "never",
      "password": "dazp^dkaz",
      "id": 398
    },
    {
      "signin": "never",
      "password": "dazp^dkaz",
      "id": 399
    },
    {
      "signin": "never",
      "password": "dazp^dkaz",
      "id": 400
    },
    {
      "signin": "never",
      "password": "dazp^dkaz",
      "id": 401
    },
    {
      "signin": "never",
      "password": "dazp^dkaz",
      "id": 402
    },
    {
      "signin": "never",
      "password": "dazp^dkaz",
      "id": 403
    },
    {
      "signin": "never",
      "password": "dazp^dkaz",
      "id": 404
    },
    {
      "signin": "never",
      "password": "dazp^dkaz",
      "id": 405
    },
    {
      "signin": "never",
      "password": "dazp^dkaz",
      "id": 406
    },
    {
      "signin": "never",
      "password": "dazp^dkaz",
      "id": 407
    },
    {
      "signin": "never",
      "password": "dazp^dkaz",
      "id": 408
    },
    {
      "signin": "never",
      "password": "dazp^dkaz",
      "id": 409
    },
    {
      "signin": "never",
      "password": "dazp^dkaz",
      "id": 410
    },
    {
      "signin": "never",
      "password": "dazp^dkaz",
      "id": 411
    },
    {
      "signin": "never",
      "password": "dazp^dkaz",
      "id": 412
    },
    {
      "signin": "never",
      "password": "dazp^dkaz",
      "id": 413
    },
    {
      "signin": "never",
      "password": "d,zad,zma",
      "id": 414
    },
    {
      "signin": "never",
      "password": "d,zad,zma",
      "id": 415
    },
    {
      "signin": "never",
      "password": "d,zad,zma",
      "id": 416
    },
    {
      "signin": "never",
      "password": "d,zad,zma",
      "id": 417
    },
    {
      "signin": "never",
      "password": "d,zad,zma",
      "id": 418
    },
    {
      "signin": "never",
      "password": "d,zad,zma",
      "id": 419
    },
    {
      "signin": "never",
      "password": "d,zad,zma",
      "id": 420
    },
    {
      "signin": "never",
      "password": "d,zad,zma",
      "id": 421
    },
    {
      "signin": "never",
      "password": "d,zad,zma",
      "id": 422
    },
    {
      "signin": "never",
      "password": "d,zad,zma",
      "id": 423
    },
    {
      "signin": "never",
      "password": "d,zad,zma",
      "id": 424
    },
    {
      "signin": "never",
      "password": "d,zad,zma",
      "id": 425
    },
    {
      "signin": "never",
      "password": "d,zad,zma",
      "id": 426
    },
    {
      "signin": "never",
      "password": "d,zad,zma",
      "id": 427
    },
    {
      "signin": "never",
      "password": "d,zad,zma",
      "id": 428
    },
    {
      "signin": "never",
      "password": "d,zad,zma",
      "id": 429
    },
    {
      "signin": "never",
      "password": "d,zad,zma",
      "id": 430
    },
    {
      "signin": "never",
      "password": "d,zad,zma",
      "id": 431
    },
    {
      "signin": "never",
      "password": "d,zad,zma",
      "id": 432
    },
    {
      "signin": "never",
      "password": "d,zad,zma",
      "id": 433
    },
    {
      "signin": "never",
      "password": "d,maz,d",
      "id": 434
    },
    {
      "signin": "never",
      "password": "d,maz,d",
      "id": 435
    },
    {
      "signin": "never",
      "password": "d,maz,d",
      "id": 436
    },
    {
      "signin": "never",
      "password": "d,maz,d",
      "id": 437
    },
    {
      "signin": "never",
      "password": "d,maz,d",
      "id": 438
    },
    {
      "signin": "never",
      "password": "d,maz,d",
      "id": 439
    },
    {
      "signin": "never",
      "password": "d,maz,d",
      "id": 440
    },
    {
      "signin": "never",
      "password": "d,maz,d",
      "id": 441
    },
    {
      "signin": "never",
      "password": "d,maz,d",
      "id": 442
    },
    {
      "signin": "never",
      "password": "d,maz,d",
      "id": 443
    },
    {
      "signin": "never",
      "password": "d,maz,d",
      "id": 444
    },
    {
      "signin": "pdefine",
      "password": "d,za,d",
      "id": 445
    },
    {
      "signin": "pdefine2",
      "password": "isitok?",
      "id": 446
    },
    {
      "signin": "NEWaccount",
      "password": "newpass",
      "id": 447
    },
    {
      "signin": "LOG",
      "password": "LOGPASS",
      "id": 448
    },
    {
      "signin": "NewUser1",
      "password": "newpass1",
      "id": 449
    },
    {
      "signin": "randomp1",
      "password": "random1",
      "id": 450
    },
    {
      "signin": "lasttryuser",
      "password": "lasttrypass",
      "id": 451
    },
    {
      "signin": "fgnnnnn",
      "password": "aaa",
      "id": 452
    },
    {
      "signin": "klmfunct",
      "password": "okpass",
      "id": 453
    },
    {
      "signin": "admin999",
      "password": "finished",
      "id": 454
    },
    {
      "signin": "derder",
      "password": "derpass",
      "id": 455
    },
    {
      "signin": "xxxxxxxx111111111111",
      "password": "xx",
      "id": 456
    },
    {
      "signin": "newmessage",
      "password": "mewpass",
      "id": 457
    },
    {
      "signin": "newmessage2",
      "password": "mewpass",
      "id": 458
    },
    {
      "signin": "newmessage3",
      "password": "mewpass",
      "id": 459
    },
    {
      "signin": "admin123",
      "password": "admin123",
      "id": 460
    },
    {
      "signin": "admin456",
      "password": "ad456",
      "id": 461
    },
    {
      "signin": "lastusernametest",
      "password": "lastpasstest",
      "id": 462
    }
  ]
}